{"type":"FeatureCollection","features":[{"type":"Feature","properties":{"c":"E01028285","n":"Newark and Sherwood 011A","d":6,"s":14.2,"r":20176,"id":6,"ed":6,"hd":5,"cd":5,"bd":9,"ld":4,"p":1188,"wbi":90.0,"wir":0.3,"wgy":0.1,"wro":0.1,"wot":6.3,"ind":0.3,"pak":0.2,"chi":0.4,"bca":0.3,"baf":0.3,"mwc":0.8,"mwas":0.3,"mot":0.3,"ara":0.1,"oet":0.3,"a04":4.3,"a511":8.4,"a1217":6.4,"a1824":6.9,"a2534":13.3,"a3544":12.2,"a4559":23.0,"a6074":19.1,"a75p":6.4},"geometry":{"type":"Polygon","coordinates":[[[-0.78169,53.05863],[-0.78739,53.06098],[-0.79597,53.06292],[-0.79277,53.06594],[-0.79113,53.06587],[-0.78797,53.0674],[-0.77936,53.06507],[-0.78169,53.05863]]]}},{"type":"Feature","properties":{"c":"E01028286","n":"Newark and Sherwood 011B","d":5,"s":20.4,"r":14389,"id":4,"ed":5,"hd":4,"cd":6,"bd":7,"ld":8,"p":1351,"wbi":94.6,"wir":0.2,"wro":0.2,"wot":3.3,"ind":0.4,"oas":0.1,"bca":0.3,"bot":0.2,"mwc":0.1,"mwa":0.3,"mwas":0.4,"mot":0.1,"a04":4.6,"a511":7.0,"a1217":6.3,"a1824":5.3,"a2534":10.7,"a3544":9.1,"a4559":19.8,"a6074":21.7,"a75p":15.4},"geometry":{"type":"Polygon","coordinates":[[[-0.74543,53.05412],[-0.74969,53.05512],[-0.74974,53.05503],[-0.75344,53.04806],[-0.76133,53.05302],[-0.76753,53.05661],[-0.77706,53.05738],[-0.77444,53.0619],[-0.78169,53.05863],[-0.77936,53.06507],[-0.78797,53.0674],[-0.76993,53.07134],[-0.76646,53.07226],[-0.76166,53.066],[-0.75244,53.06294],[-0.75457,53.05604],[-0.74835,53.0552],[-0.74543,53.05412]]]}},{"type":"Feature","properties":{"c":"E01028287","n":"Newark and Sherwood 011C","d":7,"s":13.6,"r":20859,"id":6,"ed":6,"hd":5,"cd":6,"bd":9,"ld":6,"p":1518,"wbi":93.4,"wir":0.7,"wgy":0.3,"wro":0.2,"wot":2.7,"ind":0.4,"ban":0.4,"chi":0.1,"oas":0.1,"bca":0.5,"baf":0.2,"mwc":0.2,"mwas":0.4,"ara":0.1,"oet":0.4,"a04":3.8,"a511":7.3,"a1217":7.0,"a1824":6.8,"a2534":9.2,"a3544":11.2,"a4559":22.3,"a6074":17.0,"a75p":15.5},"geometry":{"type":"Polygon","coordinates":[[[-0.77706,53.05738],[-0.78075,53.05208],[-0.78462,53.05686],[-0.78739,53.06098],[-0.78169,53.05863],[-0.77444,53.0619],[-0.77706,53.05738]]]}},{"type":"Feature","properties":{"c":"E01028288","n":"Newark and Sherwood 011D","d":8,"s":9.6,"r":25470,"id":7,"ed":7,"hd":8,"cd":7,"bd":8,"ld":7,"p":1436,"wbi":94.5,"wir":0.4,"wgy":0.1,"wot":2.5,"ind":0.3,"chi":0.1,"oas":0.3,"bca":0.3,"mwc":0.5,"mwa":0.1,"mwas":0.7,"mot":0.2,"a04":4.1,"a511":5.7,"a1217":5.9,"a1824":6.8,"a2534":10.7,"a3544":8.5,"a4559":22.9,"a6074":20.7,"a75p":14.8},"geometry":{"type":"Polygon","coordinates":[[[-0.76753,53.05661],[-0.77855,53.05029],[-0.78075,53.05208],[-0.77706,53.05738],[-0.76753,53.05661]]]}},{"type":"Feature","properties":{"c":"E01028289","n":"Newark and Sherwood 011E","d":7,"s":11.9,"r":22700,"id":7,"ed":6,"hd":6,"cd":4,"bd":9,"ld":7,"p":1304,"wbi":92.6,"wir":1.0,"wgy":0.1,"wro":0.1,"wot":2.9,"ind":0.3,"pak":0.1,"ban":0.3,"chi":0.1,"oas":1.5,"baf":0.1,"mwc":0.1,"mwa":0.1,"mwas":0.4,"mot":0.1,"oet":0.2,"a04":4.1,"a511":5.3,"a1217":4.4,"a1824":5.3,"a2534":12.3,"a3544":10.9,"a4559":19.2,"a6074":22.8,"a75p":15.8},"geometry":{"type":"Polygon","coordinates":[[[-0.78739,53.06098],[-0.78462,53.05686],[-0.78515,53.05672],[-0.79777,53.05769],[-0.79655,53.06123],[-0.79597,53.06292],[-0.78739,53.06098]]]}},{"type":"Feature","properties":{"c":"E01028290","n":"Newark and Sherwood 011F","d":5,"s":17.9,"r":16426,"id":4,"ed":5,"hd":5,"cd":6,"bd":8,"ld":9,"p":1434,"wbi":90.9,"wir":0.9,"wgy":0.1,"wot":3.4,"ind":0.9,"chi":0.4,"oas":0.6,"bca":0.1,"baf":0.6,"bot":0.3,"mwc":0.8,"mwa":0.1,"mwas":0.2,"mot":0.4,"oet":0.3,"a04":4.3,"a511":8.3,"a1217":7.1,"a1824":6.5,"a2534":11.2,"a3544":10.2,"a4559":18.3,"a6074":21.1,"a75p":13.0},"geometry":{"type":"Polygon","coordinates":[[[-0.78075,53.05208],[-0.77855,53.05029],[-0.77904,53.05],[-0.79087,53.04461],[-0.79185,53.0504],[-0.78515,53.05672],[-0.78462,53.05686],[-0.78075,53.05208]]]}},{"type":"Feature","properties":{"c":"E01028291","n":"Newark and Sherwood 011G","d":5,"s":17.8,"r":16526,"id":5,"ed":4,"hd":5,"cd":4,"bd":7,"ld":10,"p":2315,"wbi":89.9,"wir":0.3,"wgy":0.2,"wro":0.1,"wot":5.2,"ind":0.8,"pak":0.1,"chi":0.2,"oas":0.7,"bca":0.1,"baf":0.2,"bot":0.1,"mwc":1.2,"mwa":0.1,"mwas":0.4,"mot":0.2,"a04":6.6,"a511":10.2,"a1217":6.0,"a1824":8.6,"a2534":18.5,"a3544":12.8,"a4559":18.8,"a6074":12.2,"a75p":6.4},"geometry":{"type":"Polygon","coordinates":[[[-0.79777,53.05769],[-0.78515,53.05672],[-0.79185,53.0504],[-0.79087,53.04461],[-0.7972,53.0428],[-0.80351,53.04868],[-0.80597,53.05726],[-0.80567,53.05787],[-0.79777,53.05769]]]}},{"type":"Feature","properties":{"c":"E01028292","n":"Newark and Sherwood 009A","d":9,"s":5.8,"r":29941,"id":8,"ed":9,"hd":8,"cd":9,"bd":5,"ld":10,"p":2771,"wbi":90.6,"wir":0.4,"wgy":0.1,"wot":3.9,"ind":0.6,"ban":0.3,"chi":0.4,"oas":0.2,"bca":0.4,"baf":0.5,"bot":0.1,"mwc":0.4,"mwa":0.1,"mwas":0.4,"mot":0.4,"ara":0.4,"oet":0.7,"a04":5.2,"a511":8.2,"a1217":7.2,"a1824":6.6,"a2534":12.3,"a3544":13.1,"a4559":21.8,"a6074":17.2,"a75p":8.4},"geometry":{"type":"Polygon","coordinates":[[[-0.76993,53.07134],[-0.78797,53.0674],[-0.79113,53.06587],[-0.79477,53.07132],[-0.78249,53.0713],[-0.77943,53.07432],[-0.79175,53.07629],[-0.79176,53.07633],[-0.77465,53.08367],[-0.76993,53.07134]]]}},{"type":"Feature","properties":{"c":"E01028293","n":"Newark and Sherwood 009B","d":7,"s":13.3,"r":21169,"id":6,"ed":7,"hd":7,"cd":6,"bd":9,"ld":3,"p":1921,"wbi":81.2,"wir":0.7,"wgy":0.1,"wro":0.2,"wot":11.4,"ind":0.7,"pak":0.3,"ban":0.1,"chi":0.9,"oas":1.0,"bca":0.1,"baf":0.4,"mwc":0.4,"mwa":0.4,"mwas":1.0,"mot":0.4,"ara":0.2,"oet":0.8,"a04":5.7,"a511":8.3,"a1217":6.4,"a1824":8.1,"a2534":14.2,"a3544":13.3,"a4559":20.5,"a6074":15.9,"a75p":7.6},"geometry":{"type":"Polygon","coordinates":[[[-0.79113,53.06587],[-0.79277,53.06594],[-0.79922,53.06968],[-0.79175,53.07629],[-0.77943,53.07432],[-0.78249,53.0713],[-0.79477,53.07132],[-0.79113,53.06587]]]}},{"type":"Feature","properties":{"c":"E01028294","n":"Newark and Sherwood 007A","d":4,"s":26.3,"r":10288,"id":3,"ed":4,"hd":3,"cd":4,"bd":10,"ld":2,"p":1985,"wbi":79.6,"wir":0.4,"wgy":0.1,"wro":0.3,"wot":14.4,"ind":0.3,"pak":0.1,"ban":0.1,"chi":0.3,"oas":0.7,"bca":0.5,"bot":0.1,"mwc":0.9,"mwa":0.4,"mwas":0.2,"mot":0.3,"ara":0.3,"oet":1.2,"a04":7.8,"a511":7.5,"a1217":5.4,"a1824":7.7,"a2534":18.7,"a3544":14.7,"a4559":18.4,"a6074":13.6,"a75p":6.2},"geometry":{"type":"Polygon","coordinates":[[[-0.79175,53.07629],[-0.79922,53.06968],[-0.80491,53.07188],[-0.80394,53.07486],[-0.79591,53.0763],[-0.79176,53.07633],[-0.79175,53.07629]]]}},{"type":"Feature","properties":{"c":"E01028295","n":"Newark and Sherwood 005A","d":8,"s":10.1,"r":24793,"id":8,"ed":6,"hd":7,"cd":8,"bd":3,"ld":9,"p":1925,"wbi":96.0,"wir":0.3,"wgy":0.1,"wot":1.0,"ind":0.5,"pak":0.1,"chi":0.1,"oas":0.2,"bca":0.1,"bot":0.1,"mwc":0.4,"mwa":0.2,"mwas":0.6,"mot":0.4,"oet":0.2,"a04":4.3,"a511":5.2,"a1217":5.8,"a1824":6.0,"a2534":9.1,"a3544":10.0,"a4559":25.5,"a6074":21.7,"a75p":12.3},"geometry":{"type":"Polygon","coordinates":[[[-0.9673,53.15879],[-0.97464,53.16099],[-1.00922,53.16092],[-1.01598,53.1592],[-1.02031,53.1534],[-1.041,53.14196],[-1.03544,53.13791],[-1.02519,53.13846],[-1.00448,53.13775],[-1.02093,53.12242],[-1.06214,53.12006],[-1.07085,53.11408],[-1.09755,53.11688],[-1.09693,53.1268],[-1.11109,53.15324],[-1.11106,53.15343],[-1.08107,53.15851],[-1.07272,53.16704],[-1.05146,53.17766],[-1.03301,53.18344],[-1.00596,53.18894],[-1.00128,53.17634],[-0.99058,53.1766],[-0.97162,53.16909],[-0.95734,53.16779],[-0.9673,53.15879]]]}},{"type":"Feature","properties":{"c":"E01028296","n":"Newark and Sherwood 006A","d":4,"s":24.4,"r":11517,"id":5,"ed":3,"hd":3,"cd":3,"bd":6,"ld":8,"p":1851,"wbi":93.4,"wgy":0.3,"wot":2.9,"ind":0.3,"pak":0.2,"chi":0.3,"oas":0.4,"bca":0.2,"baf":0.2,"bot":0.1,"mwc":0.7,"mwa":0.2,"mwas":0.2,"mot":0.3,"ara":0.2,"oet":0.3,"a04":6.4,"a511":9.6,"a1217":6.5,"a1824":6.5,"a2534":15.3,"a3544":12.5,"a4559":19.9,"a6074":14.8,"a75p":8.6},"geometry":{"type":"Polygon","coordinates":[[[-1.09755,53.11688],[-1.10957,53.11839],[-1.11705,53.11907],[-1.12022,53.11908],[-1.12724,53.1245],[-1.12844,53.13295],[-1.12874,53.13894],[-1.1288,53.14334],[-1.11109,53.15324],[-1.09693,53.1268],[-1.09755,53.11688]]]}},{"type":"Feature","properties":{"c":"E01028297","n":"Newark and Sherwood 005B","d":3,"s":31.7,"r":7485,"id":3,"ed":2,"hd":2,"cd":4,"bd":3,"ld":9,"p":2036,"wbi":95.3,"wir":0.4,"wgy":0.5,"wot":2.1,"ind":0.3,"chi":0.2,"bca":0.2,"baf":0.2,"bot":0.2,"mwc":0.5,"mwa":0.1,"mwas":0.2,"mot":0.2,"a04":5.2,"a511":9.8,"a1217":7.2,"a1824":7.4,"a2534":11.7,"a3544":11.4,"a4559":21.8,"a6074":17.7,"a75p":7.8},"geometry":{"type":"Polygon","coordinates":[[[-1.02519,53.13846],[-1.03544,53.13791],[-1.041,53.14196],[-1.02031,53.1534],[-1.02519,53.13846]]]}},{"type":"Feature","properties":{"c":"E01028298","n":"Newark and Sherwood 006B","d":6,"s":16.2,"r":18016,"id":6,"ed":5,"hd":5,"cd":7,"bd":5,"ld":6,"p":1501,"wbi":95.6,"wir":0.5,"wot":0.8,"ind":0.4,"chi":0.2,"oas":0.4,"bca":0.2,"baf":0.1,"mwc":1.0,"mwa":0.2,"mwas":0.5,"mot":0.1,"ara":0.1,"a04":3.5,"a511":7.2,"a1217":6.2,"a1824":6.3,"a2534":11.7,"a3544":10.3,"a4559":24.7,"a6074":20.4,"a75p":9.7},"geometry":{"type":"Polygon","coordinates":[[[-1.11396,53.10461],[-1.11343,53.10106],[-1.12213,53.0982],[-1.11285,53.09601],[-1.11847,53.09509],[-1.11506,53.09062],[-1.13109,53.08814],[-1.14006,53.09231],[-1.13923,53.09966],[-1.15767,53.09901],[-1.15996,53.10396],[-1.13164,53.11487],[-1.12457,53.10555],[-1.11396,53.10461]]]}},{"type":"Feature","properties":{"c":"E01028299","n":"Newark and Sherwood 006C","d":2,"s":35.4,"r":6009,"id":2,"ed":2,"hd":2,"cd":6,"bd":5,"ld":9,"p":1215,"wbi":93.8,"wir":0.1,"wgy":0.2,"wot":3.8,"oas":0.4,"mwc":1.1,"mwa":0.3,"mwas":0.1,"mot":0.3,"oet":0.1,"a04":6.3,"a511":9.9,"a1217":7.5,"a1824":7.2,"a2534":14.2,"a3544":13.0,"a4559":23.0,"a6074":13.8,"a75p":5.1},"geometry":{"type":"Polygon","coordinates":[[[-1.08827,53.09674],[-1.11343,53.10106],[-1.11396,53.10461],[-1.10231,53.11283],[-1.09789,53.11633],[-1.10213,53.11277],[-1.08827,53.09674]]]}},{"type":"Feature","properties":{"c":"E01028300","n":"Newark and Sherwood 006D","d":2,"s":36.8,"r":5516,"id":3,"ed":2,"hd":1,"cd":4,"bd":5,"ld":7,"p":1469,"wbi":94.0,"wir":0.6,"wro":0.1,"wot":2.6,"ind":0.3,"oas":0.1,"bca":0.2,"baf":0.5,"mwc":0.4,"mwa":0.4,"mwas":0.2,"mot":0.5,"oet":0.1,"a04":5.2,"a511":8.1,"a1217":6.4,"a1824":6.9,"a2534":15.1,"a3544":12.5,"a4559":19.3,"a6074":17.3,"a75p":9.3},"geometry":{"type":"Polygon","coordinates":[[[-1.08827,53.09674],[-1.0836,53.09702],[-1.08328,53.08759],[-1.0895,53.07802],[-1.09432,53.07415],[-1.11396,53.07701],[-1.13018,53.07361],[-1.12064,53.08675],[-1.13109,53.08814],[-1.11506,53.09062],[-1.11847,53.09509],[-1.11285,53.09601],[-1.12213,53.0982],[-1.11343,53.10106],[-1.08827,53.09674]]]}},{"type":"Feature","properties":{"c":"E01028301","n":"Newark and Sherwood 001A","d":1,"s":52.8,"r":1909,"id":1,"ed":1,"hd":2,"cd":2,"bd":3,"ld":8,"p":1965,"wbi":93.7,"wir":0.2,"wgy":0.2,"wot":3.2,"ind":0.1,"pak":0.2,"ban":0.1,"chi":0.1,"baf":0.1,"bot":0.1,"mwc":1.0,"mwa":0.2,"mwas":0.4,"mot":0.3,"ara":0.1,"a04":7.7,"a511":13.1,"a1217":8.7,"a1824":9.8,"a2534":15.1,"a3544":12.7,"a4559":17.4,"a6074":10.5,"a75p":5.0},"geometry":{"type":"Polygon","coordinates":[[[-0.97082,53.20286],[-0.98222,53.19934],[-0.98971,53.2079],[-0.98698,53.20674],[-0.98454,53.21124],[-1.00257,53.20809],[-1.00254,53.21252],[-1.00447,53.22463],[-0.97009,53.21869],[-0.97767,53.21728],[-0.9737,53.2115],[-0.98048,53.2056],[-0.97082,53.20286]]]}},{"type":"Feature","properties":{"c":"E01028302","n":"Newark and Sherwood 001B","d":5,"s":19.8,"r":14904,"id":5,"ed":4,"hd":3,"cd":5,"bd":6,"ld":8,"p":1547,"wbi":96.8,"wir":0.2,"wgy":0.3,"wot":1.6,"ind":0.2,"chi":0.1,"bca":0.1,"baf":0.1,"mwc":0.1,"mwa":0.3,"mwas":0.2,"oet":0.1,"a04":3.6,"a511":6.1,"a1217":5.3,"a1824":6.8,"a2534":10.9,"a3544":9.4,"a4559":24.1,"a6074":21.2,"a75p":12.6},"geometry":{"type":"Polygon","coordinates":[[[-0.98222,53.19934],[-1.00212,53.19245],[-1.00198,53.20084],[-1.00257,53.20809],[-0.98454,53.21124],[-0.98698,53.20674],[-0.98971,53.2079],[-0.98222,53.19934]]]}},{"type":"Feature","properties":{"c":"E01028303","n":"Newark and Sherwood 003A","d":6,"s":15.8,"r":18411,"id":7,"ed":5,"hd":5,"cd":9,"bd":2,"ld":7,"p":1488,"wbi":97.2,"wir":0.2,"wgy":0.1,"wot":0.9,"ind":0.1,"ban":0.1,"chi":0.3,"oas":0.1,"bca":0.1,"baf":0.1,"mwc":0.2,"mwas":0.3,"mot":0.1,"oet":0.3,"a04":3.0,"a511":4.8,"a1217":5.3,"a1824":5.5,"a2534":7.0,"a3544":8.6,"a4559":21.5,"a6074":28.4,"a75p":16.0},"geometry":{"type":"Polygon","coordinates":[[[-0.95019,53.22619],[-0.94722,53.22576],[-0.94929,53.21431],[-0.93985,53.21549],[-0.93974,53.20639],[-0.9439,53.20388],[-0.95837,53.19968],[-0.97082,53.20286],[-0.98048,53.2056],[-0.9737,53.2115],[-0.97767,53.21728],[-0.97009,53.21869],[-1.00447,53.22463],[-1.00665,53.23603],[-1.01361,53.23761],[-1.01292,53.24164],[-1.00659,53.23612],[-0.96754,53.23533],[-0.95019,53.22619]]]}},{"type":"Feature","properties":{"c":"E01028304","n":"Newark and Sherwood 007B","d":3,"s":32.8,"r":7037,"id":2,"ed":1,"hd":2,"cd":8,"bd":9,"ld":6,"p":1480,"wbi":73.8,"wir":0.6,"wgy":0.1,"wot":20.0,"ind":0.7,"pak":0.2,"ban":0.1,"chi":0.3,"oas":0.8,"bca":0.3,"baf":0.3,"bot":0.1,"mwc":0.5,"mwa":0.5,"mwas":0.8,"mot":0.1,"oet":0.7,"a04":5.3,"a511":9.2,"a1217":7.2,"a1824":6.4,"a2534":13.9,"a3544":15.5,"a4559":18.6,"a6074":15.7,"a75p":8.3},"geometry":{"type":"Polygon","coordinates":[[[-0.77465,53.08367],[-0.79176,53.07633],[-0.79591,53.0763],[-0.79905,53.08526],[-0.79364,53.08795],[-0.78583,53.0857],[-0.7892,53.09314],[-0.78671,53.09373],[-0.77465,53.08367]]]}},{"type":"Feature","properties":{"c":"E01028305","n":"Newark and Sherwood 007C","d":4,"s":22.4,"r":12838,"id":4,"ed":3,"hd":5,"cd":4,"bd":10,"ld":2,"p":1609,"wbi":76.3,"wir":0.2,"wgy":1.1,"wro":0.3,"wot":15.5,"ind":0.8,"pak":0.2,"ban":0.5,"chi":0.5,"oas":0.3,"bca":0.4,"baf":0.5,"mwc":0.9,"mwa":0.5,"mwas":1.0,"mot":0.5,"ara":0.4,"oet":0.3,"a04":6.4,"a511":8.4,"a1217":6.2,"a1824":8.2,"a2534":18.9,"a3544":14.2,"a4559":18.4,"a6074":13.0,"a75p":6.2},"geometry":{"type":"Polygon","coordinates":[[[-0.79591,53.0763],[-0.80394,53.07486],[-0.80387,53.0787],[-0.80124,53.08442],[-0.79905,53.08526],[-0.79591,53.0763]]]}},{"type":"Feature","properties":{"c":"E01028306","n":"Newark and Sherwood 007D","d":4,"s":26.4,"r":10250,"id":3,"ed":2,"hd":4,"cd":3,"bd":8,"ld":7,"p":1683,"wbi":82.5,"wir":0.4,"wgy":0.3,"wot":12.1,"ind":0.4,"pak":0.4,"ban":0.5,"chi":0.1,"oas":0.2,"bca":0.2,"baf":0.2,"bot":0.1,"mwc":0.9,"mwa":0.4,"mwas":0.6,"mot":0.1,"ara":0.1,"oet":0.5,"a04":6.7,"a511":9.3,"a1217":7.5,"a1824":7.3,"a2534":13.2,"a3544":14.6,"a4559":20.5,"a6074":14.5,"a75p":6.4},"geometry":{"type":"Polygon","coordinates":[[[-0.78671,53.09373],[-0.7892,53.09314],[-0.79894,53.0953],[-0.79152,53.09097],[-0.79631,53.09045],[-0.79364,53.08795],[-0.79905,53.08526],[-0.80124,53.08442],[-0.80691,53.09007],[-0.80338,53.09726],[-0.7989,53.10142],[-0.78671,53.09373]]]}},{"type":"Feature","properties":{"c":"E01028307","n":"Newark and Sherwood 007E","d":7,"s":12.4,"r":22156,"id":7,"ed":5,"hd":6,"cd":7,"bd":7,"ld":5,"p":1234,"wbi":78.9,"wir":0.4,"wgy":0.7,"wro":0.2,"wot":15.1,"ind":1.4,"pak":0.1,"ban":0.4,"chi":0.1,"bca":0.2,"baf":0.7,"mwc":0.2,"mwa":0.1,"ara":0.5,"oet":1.2,"a04":5.1,"a511":7.0,"a1217":5.2,"a1824":7.2,"a2534":16.4,"a3544":13.9,"a4559":21.6,"a6074":18.8,"a75p":4.8},"geometry":{"type":"Polygon","coordinates":[[[-0.7892,53.09314],[-0.78583,53.0857],[-0.79364,53.08795],[-0.79631,53.09045],[-0.79152,53.09097],[-0.79894,53.0953],[-0.7892,53.09314]]]}},{"type":"Feature","properties":{"c":"E01028308","n":"Newark and Sherwood 010A","d":6,"s":15.6,"r":18717,"id":6,"ed":5,"hd":6,"cd":5,"bd":10,"ld":6,"p":1609,"wbi":88.5,"wir":1.2,"wgy":0.4,"wro":0.1,"wot":6.8,"ind":0.8,"pak":0.4,"chi":0.2,"bca":0.1,"baf":0.4,"mwc":0.4,"mwas":0.1,"mot":0.4,"oet":0.3,"a04":3.5,"a511":6.1,"a1217":4.9,"a1824":4.4,"a2534":9.7,"a3544":9.9,"a4559":21.5,"a6074":25.8,"a75p":14.2},"geometry":{"type":"Polygon","coordinates":[[[-0.81516,53.07028],[-0.80839,53.06779],[-0.80836,53.06775],[-0.80906,53.06505],[-0.81238,53.06383],[-0.81749,53.06761],[-0.81991,53.06506],[-0.8264,53.0655],[-0.81971,53.07194],[-0.81593,53.07419],[-0.81516,53.07028]]]}},{"type":"Feature","properties":{"c":"E01028309","n":"Newark and Sherwood 010B","d":8,"s":10.0,"r":24969,"id":9,"ed":8,"hd":5,"cd":5,"bd":7,"ld":9,"p":1379,"wbi":92.0,"wir":0.9,"wro":0.1,"wot":2.5,"ind":0.2,"ban":0.1,"chi":0.5,"oas":0.6,"bca":0.1,"baf":0.5,"bot":0.1,"mwc":0.6,"mwas":0.2,"mot":0.9,"ara":0.1,"oet":0.7,"a04":2.8,"a511":5.4,"a1217":3.8,"a1824":5.5,"a2534":10.6,"a3544":11.4,"a4559":22.3,"a6074":25.3,"a75p":12.8},"geometry":{"type":"Polygon","coordinates":[[[-0.81991,53.06506],[-0.82427,53.06122],[-0.8262,53.05861],[-0.83154,53.05849],[-0.83031,53.06213],[-0.84045,53.06681],[-0.82954,53.0713],[-0.81971,53.07194],[-0.8264,53.0655],[-0.81991,53.06506]]]}},{"type":"Feature","properties":{"c":"E01028310","n":"Newark and Sherwood 007F","d":2,"s":35.7,"r":5924,"id":3,"ed":2,"hd":3,"cd":1,"bd":10,"ld":2,"p":2215,"wbi":73.7,"wir":1.0,"wgy":0.3,"wro":1.0,"wot":17.3,"ind":0.3,"pak":0.1,"ban":0.6,"chi":0.6,"oas":1.5,"bca":0.1,"baf":0.3,"mwc":0.5,"mwa":0.3,"mwas":0.5,"mot":0.4,"ara":0.8,"oet":0.8,"a04":5.8,"a511":4.5,"a1217":4.5,"a1824":11.1,"a2534":19.2,"a3544":14.8,"a4559":19.3,"a6074":14.3,"a75p":6.5},"geometry":{"type":"Polygon","coordinates":[[[-0.80691,53.09007],[-0.80124,53.08442],[-0.80387,53.0787],[-0.8098,53.07448],[-0.81276,53.07663],[-0.80781,53.08201],[-0.82421,53.07699],[-0.82546,53.07973],[-0.81611,53.08321],[-0.82185,53.09152],[-0.80691,53.09007]]]}},{"type":"Feature","properties":{"c":"E01028311","n":"Newark and Sherwood 007G","d":1,"s":50.7,"r":2249,"id":1,"ed":1,"hd":2,"cd":1,"bd":10,"ld":1,"p":1687,"wbi":75.6,"wir":0.7,"wgy":2.8,"wro":0.8,"wot":12.9,"ind":0.1,"pak":0.1,"ban":0.2,"chi":0.5,"oas":0.4,"bca":0.6,"baf":0.7,"bot":0.1,"mwc":0.3,"mwa":0.4,"mwas":0.8,"mot":1.0,"ara":0.1,"oet":1.9,"a04":5.8,"a511":5.1,"a1217":4.7,"a1824":9.1,"a2534":17.0,"a3544":13.5,"a4559":17.3,"a6074":18.1,"a75p":9.5},"geometry":{"type":"Polygon","coordinates":[[[-0.8098,53.07448],[-0.81516,53.07028],[-0.81593,53.07419],[-0.81971,53.07194],[-0.82954,53.0713],[-0.83742,53.07527],[-0.82185,53.09152],[-0.81611,53.08321],[-0.82546,53.07973],[-0.82421,53.07699],[-0.80781,53.08201],[-0.81276,53.07663],[-0.8098,53.07448]]]}},{"type":"Feature","properties":{"c":"E01028312","n":"Newark and Sherwood 003B","d":6,"s":15.7,"r":18534,"id":9,"ed":8,"hd":9,"cd":9,"bd":1,"ld":2,"p":2332,"wbi":95.5,"wir":0.3,"wgy":0.2,"wro":0.1,"wot":1.3,"ind":0.4,"chi":0.2,"oas":0.1,"baf":0.4,"bot":0.1,"mwc":0.2,"mwa":0.3,"mwas":0.3,"mot":0.5,"oet":0.1,"a04":2.4,"a511":6.6,"a1217":7.0,"a1824":4.9,"a2534":6.7,"a3544":8.7,"a4559":25.4,"a6074":26.3,"a75p":11.9},"geometry":{"type":"Polygon","coordinates":[[[-0.86943,53.21671],[-0.87981,53.19829],[-0.85782,53.197],[-0.85262,53.19589],[-0.85441,53.19127],[-0.84276,53.19119],[-0.85163,53.19025],[-0.85298,53.18623],[-0.84889,53.18468],[-0.8486,53.1768],[-0.83997,53.17428],[-0.8456,53.17253],[-0.85349,53.16048],[-0.87011,53.15778],[-0.90184,53.16428],[-0.91183,53.16099],[-0.91237,53.15764],[-0.91155,53.15249],[-0.87465,53.14456],[-0.87485,53.13588],[-0.86456,53.13384],[-0.86764,53.12829],[-0.85939,53.12736],[-0.86267,53.11825],[-0.88447,53.11686],[-0.8867,53.1136],[-0.90023,53.11472],[-0.90719,53.1146],[-0.91936,53.10754],[-0.91342,53.10458],[-0.91676,53.10181],[-0.90899,53.0986],[-0.91408,53.09343],[-0.92004,53.09364],[-0.94056,53.0943],[-0.94589,53.09726],[-0.94474,53.1024],[-0.95875,53.10657],[-0.97745,53.1203],[-0.97597,53.12709],[-0.98788,53.13365],[-0.98245,53.13369],[-0.97213,53.14027],[-0.96516,53.13901],[-0.95609,53.14782],[-0.95307,53.15319],[-0.9673,53.15879],[-0.95734,53.16779],[-0.97162,53.16909],[-0.99058,53.1766],[-1.00128,53.17634],[-1.00596,53.18894],[-1.00403,53.19145],[-1.00212,53.19245],[-0.98222,53.19934],[-0.97082,53.20286],[-0.95837,53.19968],[-0.9439,53.20388],[-0.93974,53.20639],[-0.93985,53.21549],[-0.9011,53.22146],[-0.89308,53.22351],[-0.86943,53.21671]]]}},{"type":"Feature","properties":{"c":"E01028313","n":"Newark and Sherwood 002A","d":2,"s":39.5,"r":4691,"id":2,"ed":1,"hd":2,"cd":3,"bd":5,"ld":7,"p":2018,"wbi":94.6,"wir":0.2,"wgy":0.2,"wot":2.5,"ind":0.1,"chi":0.2,"oas":0.2,"bca":0.1,"baf":0.1,"bot":0.2,"mwc":0.8,"mwas":0.4,"mot":0.3,"a04":3.7,"a511":8.5,"a1217":8.6,"a1824":6.6,"a2534":12.0,"a3544":11.2,"a4559":20.3,"a6074":17.1,"a75p":12.2},"geometry":{"type":"Polygon","coordinates":[[[-1.07272,53.16704],[-1.08107,53.15851],[-1.11106,53.15343],[-1.11897,53.15445],[-1.12802,53.15905],[-1.11571,53.16265],[-1.11696,53.16488],[-1.10757,53.17065],[-1.1132,53.17325],[-1.10833,53.17743],[-1.11379,53.17834],[-1.12067,53.17411],[-1.12334,53.18814],[-1.11957,53.19065],[-1.12779,53.18989],[-1.11696,53.19391],[-1.10236,53.19188],[-1.08917,53.18548],[-1.08209,53.18615],[-1.07384,53.18089],[-1.08288,53.17391],[-1.07272,53.16704]]]}},{"type":"Feature","properties":{"c":"E01028315","n":"Newark and Sherwood 004A","d":10,"s":5.2,"r":30698,"id":10,"ed":10,"hd":9,"cd":10,"bd":4,"ld":7,"p":1547,"wbi":96.0,"wir":0.9,"wot":1.5,"pak":0.1,"chi":0.1,"oas":0.1,"bca":0.2,"mwc":0.3,"mwa":0.1,"mwas":0.5,"mot":0.3,"a04":3.7,"a511":5.3,"a1217":5.6,"a1824":3.7,"a2534":7.1,"a3544":9.2,"a4559":20.7,"a6074":25.9,"a75p":18.9},"geometry":{"type":"Polygon","coordinates":[[[-0.78541,53.16857],[-0.7715,53.16493],[-0.76378,53.15573],[-0.75516,53.15725],[-0.73792,53.15493],[-0.7392,53.14799],[-0.74816,53.14784],[-0.74988,53.15192],[-0.75017,53.14856],[-0.75485,53.14829],[-0.7571,53.15232],[-0.76197,53.14726],[-0.76002,53.14413],[-0.74518,53.14247],[-0.74972,53.13698],[-0.76288,53.14063],[-0.76838,53.12733],[-0.77419,53.13073],[-0.77413,53.13532],[-0.79188,53.14582],[-0.79746,53.15207],[-0.78677,53.15924],[-0.80011,53.15808],[-0.80074,53.16819],[-0.79281,53.17089],[-0.78541,53.16857]]]}},{"type":"Feature","properties":{"c":"E01028316","n":"Newark and Sherwood 004B","d":7,"s":13.7,"r":20761,"id":7,"ed":7,"hd":5,"cd":9,"bd":3,"ld":8,"p":1815,"wbi":95.7,"wir":0.5,"wot":1.4,"ind":0.8,"oas":0.2,"bca":0.3,"baf":0.1,"mwc":0.2,"mwa":0.4,"mwas":0.1,"mot":0.2,"oet":0.2,"a04":3.7,"a511":5.8,"a1217":5.3,"a1824":6.1,"a2534":8.7,"a3544":9.1,"a4559":20.5,"a6074":23.6,"a75p":17.3},"geometry":{"type":"Polygon","coordinates":[[[-0.71603,53.17041],[-0.72323,53.1551],[-0.71538,53.13688],[-0.73241,53.1278],[-0.73109,53.124],[-0.71688,53.11944],[-0.72125,53.10427],[-0.72959,53.09782],[-0.73194,53.10055],[-0.74857,53.10351],[-0.75772,53.11215],[-0.75954,53.12113],[-0.76838,53.12733],[-0.76288,53.14063],[-0.74972,53.13698],[-0.74518,53.14247],[-0.76002,53.14413],[-0.76197,53.14726],[-0.7571,53.15232],[-0.75485,53.14829],[-0.75017,53.14856],[-0.74988,53.15192],[-0.74816,53.14784],[-0.7392,53.14799],[-0.73792,53.15493],[-0.75516,53.15725],[-0.74647,53.16292],[-0.73459,53.17951],[-0.71816,53.17729],[-0.71603,53.17041]]]}},{"type":"Feature","properties":{"c":"E01028317","n":"Newark and Sherwood 004C","d":5,"s":18.1,"r":16242,"id":9,"ed":6,"hd":7,"cd":7,"bd":1,"ld":2,"p":1665,"wbi":97.2,"wir":0.8,"wot":0.4,"ind":0.2,"oas":0.1,"mwc":0.2,"mwa":0.4,"mwas":0.6,"oet":0.1,"a04":3.8,"a511":5.7,"a1217":6.0,"a1824":5.8,"a2534":7.2,"a3544":9.7,"a4559":25.4,"a6074":23.4,"a75p":12.9},"geometry":{"type":"Polygon","coordinates":[[[-0.66658,53.2397],[-0.67587,53.21764],[-0.6975,53.22025],[-0.71475,53.20761],[-0.73043,53.21072],[-0.7537,53.18815],[-0.76211,53.18822],[-0.76414,53.18154],[-0.73459,53.17951],[-0.74647,53.16292],[-0.75516,53.15725],[-0.76378,53.15573],[-0.7715,53.16493],[-0.78541,53.16857],[-0.78666,53.17872],[-0.79538,53.18107],[-0.77793,53.18652],[-0.7813,53.19274],[-0.78036,53.1964],[-0.77696,53.19989],[-0.78013,53.20405],[-0.77538,53.20758],[-0.77862,53.21255],[-0.77562,53.2151],[-0.78338,53.22469],[-0.77991,53.23284],[-0.77707,53.24691],[-0.73508,53.24387],[-0.73415,53.254],[-0.69476,53.2584],[-0.69178,53.25788],[-0.68803,53.25839],[-0.66658,53.2397]]]}},{"type":"Feature","properties":{"c":"E01028318","n":"Newark and Sherwood 010C","d":2,"s":39.9,"r":4594,"id":2,"ed":1,"hd":3,"cd":2,"bd":9,"ld":8,"p":1549,"wbi":86.1,"wir":0.2,"wgy":1.6,"wot":8.5,"ind":0.1,"chi":0.1,"oas":0.4,"bca":0.4,"bot":0.1,"mwc":1.0,"mwa":0.1,"mwas":0.5,"mot":0.2,"oet":0.8,"a04":6.2,"a511":10.8,"a1217":7.8,"a1824":7.7,"a2534":14.2,"a3544":11.1,"a4559":20.4,"a6074":15.5,"a75p":6.4},"geometry":{"type":"Polygon","coordinates":[[[-0.80906,53.06505],[-0.80818,53.06111],[-0.81678,53.06223],[-0.81976,53.06369],[-0.82427,53.06122],[-0.81991,53.06506],[-0.81749,53.06761],[-0.81238,53.06383],[-0.80906,53.06505]]]}},{"type":"Feature","properties":{"c":"E01028319","n":"Newark and Sherwood 010D","d":2,"s":36.9,"r":5492,"id":2,"ed":1,"hd":2,"cd":3,"bd":6,"ld":9,"p":2096,"wbi":87.3,"wir":0.5,"wgy":0.8,"wro":0.3,"wot":7.9,"pak":0.2,"chi":0.2,"oas":0.1,"bca":0.1,"baf":0.5,"bot":0.1,"mwc":0.7,"mwas":0.1,"mot":0.5,"oet":0.3,"a04":8.4,"a511":9.3,"a1217":6.5,"a1824":7.8,"a2534":14.8,"a3544":11.1,"a4559":20.0,"a6074":13.8,"a75p":8.3},"geometry":{"type":"Polygon","coordinates":[[[-0.81678,53.06223],[-0.81228,53.05749],[-0.8262,53.05861],[-0.82427,53.06122],[-0.81976,53.06369],[-0.81678,53.06223]]]}},{"type":"Feature","properties":{"c":"E01028320","n":"Newark and Sherwood 010E","d":1,"s":54.5,"r":1662,"id":1,"ed":1,"hd":1,"cd":1,"bd":7,"ld":9,"p":1755,"wbi":83.3,"wir":0.9,"wgy":0.9,"wro":0.2,"wot":10.9,"ind":0.4,"ban":0.2,"chi":0.1,"oas":0.5,"bca":0.1,"baf":0.1,"mwc":1.0,"mwa":0.2,"mwas":0.2,"mot":0.3,"oet":0.8,"a04":8.8,"a511":11.2,"a1217":7.0,"a1824":7.6,"a2534":15.2,"a3544":12.4,"a4559":16.0,"a6074":14.5,"a75p":7.1},"geometry":{"type":"Polygon","coordinates":[[[-0.80818,53.06111],[-0.80567,53.05787],[-0.80597,53.05726],[-0.81228,53.05749],[-0.81678,53.06223],[-0.80818,53.06111]]]}},{"type":"Feature","properties":{"c":"E01028321","n":"Newark and Sherwood 002C","d":7,"s":12.0,"r":22574,"id":8,"ed":6,"hd":6,"cd":6,"bd":5,"ld":9,"p":1525,"wbi":96.0,"wir":0.5,"wot":1.6,"ind":0.2,"chi":0.1,"bca":0.1,"mwc":0.3,"mwa":0.3,"mwas":0.2,"mot":0.6,"oet":0.3,"a04":3.8,"a511":5.8,"a1217":4.7,"a1824":4.6,"a2534":7.4,"a3544":9.9,"a4559":20.4,"a6074":25.2,"a75p":18.3},"geometry":{"type":"Polygon","coordinates":[[[-1.06389,53.1952],[-1.06835,53.19658],[-1.07674,53.19231],[-1.07471,53.18884],[-1.06337,53.19078],[-1.06314,53.18561],[-1.05889,53.18509],[-1.06266,53.18371],[-1.05146,53.17766],[-1.07272,53.16704],[-1.08288,53.17391],[-1.07384,53.18089],[-1.08209,53.18615],[-1.08917,53.18548],[-1.10236,53.19188],[-1.11696,53.19391],[-1.10424,53.20886],[-1.05416,53.211],[-1.05577,53.20219],[-1.06389,53.1952]]]}},{"type":"Feature","properties":{"c":"E01028322","n":"Newark and Sherwood 002D","d":7,"s":13.9,"r":20510,"id":6,"ed":6,"hd":5,"cd":8,"bd":5,"ld":9,"p":2239,"wbi":96.5,"wir":0.4,"wot":1.2,"ind":0.2,"pak":0.1,"oas":0.4,"baf":0.1,"bot":0.2,"mwc":0.3,"mwas":0.4,"a04":4.8,"a511":7.1,"a1217":4.7,"a1824":5.8,"a2534":9.7,"a3544":11.3,"a4559":20.6,"a6074":22.5,"a75p":13.2},"geometry":{"type":"Polygon","coordinates":[[[-1.02419,53.21008],[-1.02583,53.20601],[-1.0276,53.20125],[-1.03484,53.20378],[-1.03672,53.19889],[-1.02734,53.19806],[-1.03315,53.19325],[-1.03301,53.18344],[-1.05146,53.17766],[-1.06266,53.18371],[-1.05889,53.18509],[-1.06314,53.18561],[-1.06337,53.19078],[-1.06389,53.1952],[-1.05577,53.20219],[-1.05416,53.211],[-1.04608,53.21459],[-1.0237,53.21248],[-1.02419,53.21008]]]}},{"type":"Feature","properties":{"c":"E01028323","n":"Newark and Sherwood 002E","d":5,"s":19.0,"r":15465,"id":5,"ed":4,"hd":4,"cd":6,"bd":5,"ld":7,"p":1729,"wbi":96.1,"wir":0.4,"wot":0.9,"ind":0.6,"pak":0.2,"chi":0.3,"oas":0.2,"bca":0.1,"baf":0.3,"mwc":0.5,"mwa":0.1,"mwas":0.2,"mot":0.1,"oet":0.1,"a04":6.6,"a511":8.0,"a1217":6.4,"a1824":7.9,"a2534":13.0,"a3544":11.9,"a4559":23.3,"a6074":14.8,"a75p":8.2},"geometry":{"type":"Polygon","coordinates":[[[-1.06389,53.1952],[-1.06337,53.19078],[-1.07471,53.18884],[-1.07674,53.19231],[-1.06835,53.19658],[-1.06389,53.1952]]]}},{"type":"Feature","properties":{"c":"E01028325","n":"Newark and Sherwood 012B","d":8,"s":10.5,"r":24348,"id":9,"ed":9,"hd":9,"cd":10,"bd":1,"ld":5,"p":1301,"wbi":95.5,"wir":0.5,"wot":1.5,"ind":0.4,"pak":0.1,"bca":0.1,"mwc":0.8,"mwa":0.1,"mwas":0.5,"mot":0.4,"ara":0.1,"oet":0.1,"a04":2.9,"a511":6.7,"a1217":7.6,"a1824":5.5,"a2534":6.6,"a3544":9.4,"a4559":23.7,"a6074":26.1,"a75p":11.5},"geometry":{"type":"Polygon","coordinates":[[[-0.87631,53.04356],[-0.82511,53.02059],[-0.82537,53.02465],[-0.80266,53.02491],[-0.80291,53.01741],[-0.79909,53.02131],[-0.79021,53.02213],[-0.79582,53.0106],[-0.80409,53.0125],[-0.80406,53.00639],[-0.77755,52.98381],[-0.77828,52.97692],[-0.7961,52.9767],[-0.80981,52.96598],[-0.81288,52.95744],[-0.82002,52.96046],[-0.83607,52.96792],[-0.82545,52.97333],[-0.81518,52.98562],[-0.82041,52.98782],[-0.82292,53.00099],[-0.83335,53.00772],[-0.83576,53.0057],[-0.84897,53.00966],[-0.85508,53.00667],[-0.86455,53.01134],[-0.87978,53.00635],[-0.89696,53.01662],[-0.90995,53.03023],[-0.91012,53.03593],[-0.90209,53.03848],[-0.90505,53.04869],[-0.89463,53.05483],[-0.88723,53.05429],[-0.87631,53.04356]]]}},{"type":"Feature","properties":{"c":"E01028326","n":"Newark and Sherwood 012C","d":5,"s":19.1,"r":15402,"id":5,"ed":4,"hd":5,"cd":5,"bd":4,"ld":9,"p":1298,"wbi":94.6,"wir":0.8,"wgy":0.2,"wot":2.0,"ind":0.5,"pak":0.1,"ban":0.2,"chi":0.1,"bca":0.2,"baf":0.2,"mwc":0.2,"mwa":0.2,"mwas":0.3,"mot":0.5,"ara":0.2,"oet":0.1,"a04":4.3,"a511":7.3,"a1217":5.6,"a1824":6.4,"a2534":7.8,"a3544":10.3,"a4559":20.8,"a6074":23.3,"a75p":14.2},"geometry":{"type":"Polygon","coordinates":[[[-0.86198,53.05163],[-0.86325,53.05965],[-0.85415,53.06262],[-0.84412,53.06338],[-0.85075,53.05714],[-0.84511,53.05401],[-0.85347,53.04649],[-0.86198,53.05163]]]}},{"type":"Feature","properties":{"c":"E01028327","n":"Newark and Sherwood 005C","d":8,"s":10.9,"r":23933,"id":7,"ed":8,"hd":8,"cd":9,"bd":3,"ld":8,"p":1965,"wbi":94.3,"wir":0.4,"wgy":0.1,"wot":2.0,"ind":0.8,"pak":0.5,"chi":0.5,"oas":0.2,"baf":0.4,"mwc":0.4,"mwa":0.1,"mwas":0.2,"mot":0.2,"ara":0.1,"oet":0.2,"a04":4.6,"a511":8.6,"a1217":6.9,"a1824":6.9,"a2534":9.4,"a3544":10.9,"a4559":23.5,"a6074":18.5,"a75p":10.6},"geometry":{"type":"Polygon","coordinates":[[[-1.02097,53.0996],[-1.01903,53.10769],[-1.02674,53.10366],[-1.03256,53.10705],[-1.03686,53.10421],[-1.04185,53.10768],[-1.04718,53.10315],[-1.04241,53.0993],[-1.03405,53.09918],[-1.03222,53.09586],[-1.02844,53.08942],[-1.03687,53.08836],[-1.03686,53.08567],[-1.04623,53.08748],[-1.0513,53.08518],[-1.03938,53.08362],[-1.03553,53.07534],[-1.02484,53.06818],[-1.02748,53.06522],[-1.02125,53.05902],[-1.03438,53.0585],[-1.04145,53.048],[-1.04733,53.04974],[-1.06512,53.04476],[-1.07206,53.04705],[-1.08236,53.05438],[-1.09343,53.06735],[-1.08669,53.0732],[-1.0895,53.07802],[-1.08328,53.08759],[-1.0836,53.09702],[-1.08827,53.09674],[-1.10213,53.11277],[-1.09789,53.11633],[-1.09755,53.11688],[-1.07085,53.11408],[-1.06214,53.12006],[-1.02093,53.12242],[-0.99683,53.11686],[-0.99521,53.11374],[-0.99955,53.10873],[-1.00534,53.10936],[-1.00997,53.10133],[-1.02097,53.0996]]]}},{"type":"Feature","properties":{"c":"E01028328","n":"Newark and Sherwood 005D","d":9,"s":5.5,"r":30274,"id":9,"ed":9,"hd":8,"cd":10,"bd":4,"ld":9,"p":1783,"wbi":96.3,"wir":0.4,"wgy":0.1,"wot":1.3,"ind":0.4,"pak":0.1,"chi":0.4,"oas":0.3,"bca":0.1,"mwc":0.2,"mwas":0.3,"mot":0.2,"a04":4.6,"a511":7.6,"a1217":6.0,"a1824":4.8,"a2534":8.1,"a3544":9.8,"a4559":20.0,"a6074":22.5,"a75p":16.5},"geometry":{"type":"Polygon","coordinates":[[[-1.02097,53.0996],[-1.03222,53.09586],[-1.03405,53.09918],[-1.04241,53.0993],[-1.04718,53.10315],[-1.04185,53.10768],[-1.03686,53.10421],[-1.03256,53.10705],[-1.02674,53.10366],[-1.01903,53.10769],[-1.02097,53.0996]]]}},{"type":"Feature","properties":{"c":"E01028329","n":"Newark and Sherwood 005E","d":8,"s":10.0,"r":24938,"id":10,"ed":10,"hd":9,"cd":8,"bd":2,"ld":4,"p":1627,"wbi":93.3,"wir":0.9,"wot":0.6,"ind":0.1,"pak":0.1,"chi":0.1,"oas":0.2,"bca":0.4,"baf":0.4,"mwc":0.8,"mwa":0.5,"mwas":1.3,"mot":1.1,"ara":0.1,"oet":0.2,"a04":3.1,"a511":7.6,"a1217":7.7,"a1824":6.8,"a2534":5.0,"a3544":8.8,"a4559":26.5,"a6074":23.2,"a75p":11.4},"geometry":{"type":"Polygon","coordinates":[[[-0.9673,53.15879],[-0.95307,53.15319],[-0.95609,53.14782],[-0.96516,53.13901],[-0.97213,53.14027],[-0.98245,53.13369],[-0.98788,53.13365],[-0.97597,53.12709],[-0.97745,53.1203],[-0.95875,53.10657],[-0.96782,53.09715],[-0.96513,53.09548],[-0.97074,53.09095],[-0.98474,53.07859],[-0.99841,53.07534],[-1.01504,53.06511],[-1.01426,53.07072],[-1.02484,53.06818],[-1.03553,53.07534],[-1.03938,53.08362],[-1.0513,53.08518],[-1.04623,53.08748],[-1.03686,53.08567],[-1.03687,53.08836],[-1.02844,53.08942],[-1.03222,53.09586],[-1.02097,53.0996],[-1.00997,53.10133],[-1.00534,53.10936],[-0.99955,53.10873],[-0.99521,53.11374],[-0.99683,53.11686],[-1.02093,53.12242],[-1.00448,53.13775],[-1.02519,53.13846],[-1.02031,53.1534],[-1.01598,53.1592],[-1.00922,53.16092],[-0.97464,53.16099],[-0.9673,53.15879]]]}},{"type":"Feature","properties":{"c":"E01028330","n":"Newark and Sherwood 013A","d":9,"s":6.7,"r":28903,"id":10,"ed":9,"hd":9,"cd":9,"bd":4,"ld":3,"p":1612,"wbi":94.5,"wir":0.7,"wgy":0.1,"wot":1.5,"ind":0.1,"pak":0.1,"chi":0.3,"oas":0.3,"bca":0.3,"mwc":0.6,"mwa":0.1,"mwas":0.7,"mot":0.4,"oet":0.3,"a04":3.2,"a511":5.8,"a1217":5.7,"a1824":5.8,"a2534":6.5,"a3544":8.6,"a4559":23.0,"a6074":26.4,"a75p":15.1},"geometry":{"type":"Polygon","coordinates":[[[-0.99672,53.01352],[-1.0003,53.00842],[-0.99737,53.00629],[-0.97914,53.0028],[-0.98196,52.99866],[-0.98985,52.99677],[-0.99529,52.98639],[-1.00709,52.98546],[-1.00877,52.9892],[-1.03119,52.99279],[-1.03811,52.99567],[-1.03726,52.99906],[-1.01881,53.00863],[-1.02277,53.015],[-1.00596,53.01483],[-1.00434,53.01146],[-0.99672,53.01352]]]}},{"type":"Feature","properties":{"c":"E01028331","n":"Newark and Sherwood 013B","d":7,"s":11.7,"r":22960,"id":9,"ed":6,"hd":7,"cd":6,"bd":2,"ld":5,"p":2366,"wbi":81.0,"wir":0.7,"wgy":1.4,"wot":2.7,"ind":1.1,"pak":2.0,"ban":0.8,"chi":0.1,"oas":0.4,"bca":1.3,"baf":1.5,"bot":1.6,"mwc":2.9,"mwa":0.3,"mwas":0.8,"mot":0.7,"ara":0.1,"oet":0.6,"a04":2.2,"a511":3.7,"a1217":3.6,"a1824":7.5,"a2534":19.7,"a3544":15.6,"a4559":22.6,"a6074":17.4,"a75p":7.7},"geometry":{"type":"Polygon","coordinates":[[[-1.02089,53.05899],[-1.0257,53.05512],[-1.01227,53.04902],[-1.00792,53.04266],[-0.99783,53.03972],[-0.99899,53.03531],[-0.98127,53.03105],[-0.97015,53.02353],[-0.98855,53.01213],[-0.99071,53.01666],[-0.99672,53.01352],[-1.00434,53.01146],[-1.00596,53.01483],[-1.02277,53.015],[-1.01881,53.00863],[-1.03726,52.99906],[-1.03921,53.00022],[-1.03421,53.005],[-1.04655,53.00721],[-1.0525,53.01204],[-1.04849,53.01707],[-1.02939,53.0232],[-1.04188,53.03141],[-1.05676,53.03555],[-1.06512,53.04476],[-1.04733,53.04974],[-1.04145,53.048],[-1.03438,53.0585],[-1.02125,53.05902],[-1.02089,53.05899]]]}},{"type":"Feature","properties":{"c":"E01028332","n":"Newark and Sherwood 013C","d":9,"s":5.7,"r":30161,"id":10,"ed":10,"hd":9,"cd":10,"bd":3,"ld":7,"p":1635,"wbi":93.9,"wir":0.4,"wot":2.0,"ind":0.6,"chi":0.2,"oas":0.1,"bca":0.2,"baf":0.1,"bot":0.1,"mwc":0.6,"mwas":0.5,"mot":0.4,"ara":0.1,"oet":0.7,"a04":4.3,"a511":5.5,"a1217":6.0,"a1824":6.0,"a2534":6.3,"a3544":10.0,"a4559":25.4,"a6074":24.1,"a75p":12.6},"geometry":{"type":"Polygon","coordinates":[[[-0.92702,53.02381],[-0.93152,53.01884],[-0.96081,53.00399],[-0.97596,52.98633],[-0.98737,52.98632],[-0.99529,52.98639],[-0.98985,52.99677],[-0.98196,52.99866],[-0.97914,53.0028],[-0.99737,53.00629],[-1.0003,53.00842],[-0.99672,53.01352],[-0.99071,53.01666],[-0.98855,53.01213],[-0.97015,53.02353],[-0.95056,53.01883],[-0.9354,53.02478],[-0.92702,53.02381]]]}},{"type":"Feature","properties":{"c":"E01028333","n":"Newark and Sherwood 009C","d":6,"s":17.2,"r":17077,"id":5,"ed":6,"hd":7,"cd":5,"bd":10,"ld":2,"p":1485,"wbi":91.3,"wir":0.4,"wgy":0.1,"wot":4.5,"oas":0.1,"bca":0.1,"baf":0.7,"bot":0.1,"mwc":0.8,"mwa":0.3,"mwas":0.8,"mot":0.6,"oet":0.1,"a04":5.8,"a511":7.8,"a1217":5.9,"a1824":5.7,"a2534":13.0,"a3544":12.9,"a4559":21.8,"a6074":16.2,"a75p":10.9},"geometry":{"type":"Polygon","coordinates":[[[-0.79922,53.06968],[-0.79277,53.06594],[-0.79597,53.06292],[-0.79655,53.06123],[-0.80082,53.06115],[-0.80009,53.06624],[-0.80836,53.06775],[-0.80839,53.06779],[-0.80491,53.07188],[-0.79922,53.06968]]]}},{"type":"Feature","properties":{"c":"E01028334","n":"Newark and Sherwood 009D","d":2,"s":42.6,"r":3938,"id":1,"ed":1,"hd":1,"cd":2,"bd":9,"ld":8,"p":1612,"wbi":82.9,"wir":0.4,"wgy":1.0,"wro":0.1,"wot":10.6,"ind":1.0,"ban":0.1,"chi":0.2,"oas":0.6,"bca":0.1,"baf":0.9,"bot":0.2,"mwc":1.0,"mwa":0.1,"mwas":0.2,"mot":0.2,"oet":0.4,"a04":7.1,"a511":11.7,"a1217":8.6,"a1824":8.7,"a2534":14.1,"a3544":11.9,"a4559":18.0,"a6074":12.7,"a75p":7.1},"geometry":{"type":"Polygon","coordinates":[[[-0.79655,53.06123],[-0.79777,53.05769],[-0.80567,53.05787],[-0.80818,53.06111],[-0.80906,53.06505],[-0.80836,53.06775],[-0.80009,53.06624],[-0.80082,53.06115],[-0.79655,53.06123]]]}},{"type":"Feature","properties":{"c":"E01028335","n":"Newark and Sherwood 009E","d":3,"s":30.4,"r":8107,"id":4,"ed":3,"hd":4,"cd":1,"bd":10,"ld":2,"p":1887,"wbi":74.2,"wir":0.8,"wgy":0.4,"wro":0.4,"wot":17.1,"ind":0.7,"pak":0.3,"ban":0.4,"chi":0.3,"oas":0.5,"bca":0.4,"baf":0.7,"bot":0.2,"mwc":0.6,"mwa":0.2,"mwas":0.6,"mot":0.2,"ara":0.4,"oet":1.6,"a04":5.3,"a511":6.8,"a1217":4.9,"a1824":7.7,"a2534":17.0,"a3544":14.3,"a4559":19.8,"a6074":16.2,"a75p":8.0},"geometry":{"type":"Polygon","coordinates":[[[-0.80394,53.07486],[-0.80491,53.07188],[-0.80839,53.06779],[-0.81516,53.07028],[-0.8098,53.07448],[-0.80387,53.0787],[-0.80394,53.07486]]]}},{"type":"Feature","properties":{"c":"E01028336","n":"Newark and Sherwood 012D","d":7,"s":13.2,"r":21217,"id":8,"ed":8,"hd":7,"cd":10,"bd":1,"ld":3,"p":1141,"wbi":91.8,"wir":1.2,"wot":2.5,"ind":0.6,"pak":0.3,"ban":0.1,"oas":0.1,"bca":0.3,"bot":0.1,"mwc":1.3,"mwas":0.7,"mot":0.3,"ara":0.5,"oet":0.3,"a04":3.9,"a511":6.9,"a1217":5.6,"a1824":4.8,"a2534":8.2,"a3544":10.9,"a4559":22.8,"a6074":24.9,"a75p":12.0},"geometry":{"type":"Polygon","coordinates":[[[-0.80338,53.09726],[-0.80691,53.09007],[-0.82185,53.09152],[-0.83742,53.07527],[-0.82954,53.0713],[-0.84045,53.06681],[-0.84734,53.07487],[-0.85969,53.06793],[-0.86578,53.06704],[-0.89057,53.07718],[-0.89899,53.07155],[-0.90642,53.07204],[-0.94119,53.07962],[-0.93442,53.08685],[-0.93061,53.08402],[-0.92043,53.08403],[-0.92004,53.09364],[-0.91408,53.09343],[-0.90899,53.0986],[-0.91676,53.10181],[-0.91342,53.10458],[-0.91936,53.10754],[-0.90719,53.1146],[-0.90023,53.11472],[-0.89706,53.10971],[-0.86767,53.10508],[-0.86298,53.10654],[-0.83545,53.09955],[-0.82084,53.10726],[-0.80338,53.09726]]]}},{"type":"Feature","properties":{"c":"E01028337","n":"Newark and Sherwood 003C","d":8,"s":10.0,"r":24960,"id":10,"ed":9,"hd":9,"cd":8,"bd":2,"ld":3,"p":1532,"wbi":97.0,"wir":0.3,"wro":0.1,"wot":1.4,"ind":0.3,"oas":0.2,"bca":0.1,"mwc":0.2,"mwa":0.1,"mwas":0.1,"mot":0.1,"ara":0.1,"a04":5.0,"a511":6.9,"a1217":6.2,"a1824":5.3,"a2534":5.8,"a3544":8.9,"a4559":23.9,"a6074":23.9,"a75p":14.0},"geometry":{"type":"Polygon","coordinates":[[[-0.79143,53.14206],[-0.79188,53.13591],[-0.79605,53.13308],[-0.80191,53.13374],[-0.80834,53.12276],[-0.80182,53.11695],[-0.80422,53.11048],[-0.79302,53.10795],[-0.7989,53.10142],[-0.80338,53.09726],[-0.82084,53.10726],[-0.83545,53.09955],[-0.86298,53.10654],[-0.86767,53.10508],[-0.89706,53.10971],[-0.90023,53.11472],[-0.8867,53.1136],[-0.88447,53.11686],[-0.86267,53.11825],[-0.85939,53.12736],[-0.86764,53.12829],[-0.86456,53.13384],[-0.84324,53.14311],[-0.82259,53.13844],[-0.81631,53.13412],[-0.80482,53.13654],[-0.79939,53.14224],[-0.79143,53.14206]]]}},{"type":"Feature","properties":{"c":"E01028338","n":"Newark and Sherwood 001C","d":4,"s":24.4,"r":11499,"id":4,"ed":3,"hd":3,"cd":6,"bd":8,"ld":8,"p":1794,"wbi":96.0,"wir":0.2,"wro":0.2,"wot":1.4,"ind":0.4,"pak":0.3,"oas":0.2,"bca":0.2,"baf":0.2,"bot":0.1,"mwc":0.1,"mwa":0.1,"mwas":0.4,"mot":0.2,"oet":0.1,"a04":5.6,"a511":8.0,"a1217":6.6,"a1824":6.9,"a2534":17.4,"a3544":11.2,"a4559":21.3,"a6074":16.9,"a75p":6.1},"geometry":{"type":"Polygon","coordinates":[[[-1.00257,53.20809],[-1.00198,53.20084],[-1.00711,53.20482],[-1.00977,53.20639],[-1.00585,53.20922],[-1.00254,53.21252],[-1.00257,53.20809]]]}},{"type":"Feature","properties":{"c":"E01028339","n":"Newark and Sherwood 001D","d":3,"s":27.5,"r":9619,"id":3,"ed":3,"hd":2,"cd":5,"bd":6,"ld":9,"p":1977,"wbi":92.3,"wir":0.2,"wgy":0.1,"wro":0.1,"wot":3.8,"ind":0.6,"ban":0.1,"chi":0.4,"oas":0.3,"baf":0.3,"bot":0.1,"mwc":0.7,"mwas":0.7,"mot":0.1,"oet":0.4,"a04":6.4,"a511":11.3,"a1217":6.3,"a1824":8.1,"a2534":17.0,"a3544":13.8,"a4559":20.0,"a6074":12.2,"a75p":4.9},"geometry":{"type":"Polygon","coordinates":[[[-1.01292,53.24164],[-1.01361,53.23761],[-1.00665,53.23603],[-1.00447,53.22463],[-1.00254,53.21252],[-1.00585,53.20922],[-1.01278,53.2063],[-1.02419,53.21008],[-1.0237,53.21248],[-1.04608,53.21459],[-1.05416,53.211],[-1.10424,53.20886],[-1.10394,53.21925],[-1.09732,53.21954],[-1.09525,53.22771],[-1.09544,53.23242],[-1.1033,53.23561],[-1.07248,53.24091],[-1.05215,53.2522],[-1.02745,53.26084],[-1.02355,53.2478],[-1.01292,53.24164]]]}},{"type":"Feature","properties":{"c":"E01028340","n":"Newark and Sherwood 001E","d":2,"s":36.9,"r":5485,"id":3,"ed":2,"hd":1,"cd":5,"bd":7,"ld":7,"p":1570,"wbi":96.4,"wir":0.3,"wot":2.2,"ind":0.1,"oas":0.1,"bot":0.1,"mwc":0.3,"mwas":0.6,"mot":0.1,"oet":0.1,"a04":5.1,"a511":7.1,"a1217":5.4,"a1824":9.5,"a2534":11.8,"a3544":9.1,"a4559":23.3,"a6074":20.1,"a75p":8.7},"geometry":{"type":"Polygon","coordinates":[[[-1.00585,53.20922],[-1.00977,53.20639],[-1.00711,53.20482],[-1.01471,53.20253],[-1.01146,53.19853],[-1.02429,53.20157],[-1.02583,53.20601],[-1.02419,53.21008],[-1.01278,53.2063],[-1.00585,53.20922]]]}},{"type":"Feature","properties":{"c":"E01028342","n":"Newark and Sherwood 006E","d":4,"s":24.0,"r":11774,"id":4,"ed":3,"hd":3,"cd":6,"bd":6,"ld":6,"p":1457,"wbi":94.8,"wir":0.2,"wgy":0.1,"wot":2.6,"ind":0.3,"bca":0.1,"baf":0.9,"mwc":0.3,"mwa":0.3,"mwas":0.2,"mot":0.1,"oet":0.1,"a04":6.3,"a511":10.0,"a1217":7.5,"a1824":8.0,"a2534":14.9,"a3544":12.9,"a4559":22.3,"a6074":13.3,"a75p":4.8},"geometry":{"type":"Polygon","coordinates":[[[-1.10957,53.11839],[-1.10395,53.11308],[-1.11705,53.11907],[-1.10957,53.11839]]]}},{"type":"Feature","properties":{"c":"E01028343","n":"Newark and Sherwood 006F","d":4,"s":22.9,"r":12493,"id":4,"ed":3,"hd":3,"cd":5,"bd":8,"ld":9,"p":2470,"wbi":94.5,"wir":0.1,"wgy":0.1,"wot":2.5,"chi":0.2,"oas":0.1,"baf":1.1,"bot":0.3,"mwc":0.3,"mwas":0.3,"mot":0.3,"oet":0.1,"a04":5.6,"a511":8.1,"a1217":6.6,"a1824":6.4,"a2534":15.6,"a3544":12.3,"a4559":19.8,"a6074":16.5,"a75p":9.3},"geometry":{"type":"Polygon","coordinates":[[[-1.13551,53.11874],[-1.12022,53.11908],[-1.11705,53.11907],[-1.10395,53.11308],[-1.10231,53.11283],[-1.11396,53.10461],[-1.12457,53.10555],[-1.13164,53.11487],[-1.15996,53.10396],[-1.16425,53.10327],[-1.17789,53.11481],[-1.1676,53.11597],[-1.14712,53.12196],[-1.13551,53.11874]]]}},{"type":"Feature","properties":{"c":"E01028344","n":"Newark and Sherwood 006G","d":8,"s":8.7,"r":26592,"id":8,"ed":6,"hd":6,"cd":9,"bd":5,"ld":10,"p":1335,"wbi":96.0,"wir":0.5,"wot":1.0,"pak":0.1,"chi":0.7,"oas":0.1,"bca":0.1,"bot":0.1,"mwas":0.6,"mot":0.5,"oet":0.2,"a04":3.2,"a511":5.4,"a1217":5.5,"a1824":6.5,"a2534":10.9,"a3544":8.3,"a4559":25.9,"a6074":24.6,"a75p":9.9},"geometry":{"type":"Polygon","coordinates":[[[-1.09755,53.11688],[-1.09789,53.11633],[-1.10231,53.11283],[-1.10395,53.11308],[-1.10957,53.11839],[-1.09755,53.11688]]]}},{"type":"Feature","properties":{"c":"E01028345","n":"Newark and Sherwood 008A","d":9,"s":6.9,"r":28726,"id":8,"ed":9,"hd":8,"cd":10,"bd":7,"ld":6,"p":2201,"wbi":95.0,"wir":0.3,"wot":1.6,"pak":0.3,"chi":0.5,"bca":0.1,"baf":0.2,"mwc":0.4,"mwa":0.1,"mwas":0.4,"mot":0.5,"ara":0.1,"oet":0.4,"a04":2.3,"a511":5.9,"a1217":6.9,"a1824":6.3,"a2534":5.4,"a3544":7.5,"a4559":20.6,"a6074":25.4,"a75p":19.7},"geometry":{"type":"Polygon","coordinates":[[[-0.92004,53.09364],[-0.92043,53.08403],[-0.93061,53.08402],[-0.93442,53.08685],[-0.94119,53.07962],[-0.90642,53.07204],[-0.91443,53.06614],[-0.91262,53.06371],[-0.92716,53.06369],[-0.94272,53.05696],[-0.94933,53.05876],[-0.95177,53.07002],[-0.95284,53.07707],[-0.95737,53.07894],[-0.95316,53.08296],[-0.9467,53.08198],[-0.96513,53.09548],[-0.96782,53.09715],[-0.95875,53.10657],[-0.94474,53.1024],[-0.94589,53.09726],[-0.94056,53.0943],[-0.92004,53.09364]]]}},{"type":"Feature","properties":{"c":"E01028346","n":"Newark and Sherwood 008B","d":9,"s":5.8,"r":30006,"id":8,"ed":9,"hd":9,"cd":10,"bd":6,"ld":8,"p":2175,"wbi":93.3,"wir":0.6,"wgy":0.1,"wot":1.5,"ind":0.2,"chi":1.1,"oas":0.3,"baf":0.3,"bot":0.1,"mwc":0.5,"mwa":0.2,"mwas":0.9,"mot":0.2,"ara":0.3,"oet":0.4,"a04":3.2,"a511":7.0,"a1217":6.8,"a1824":7.0,"a2534":6.4,"a3544":10.3,"a4559":21.0,"a6074":21.7,"a75p":16.5},"geometry":{"type":"Polygon","coordinates":[[[-0.95737,53.07894],[-0.96242,53.08247],[-0.9629,53.08711],[-0.97074,53.09095],[-0.96513,53.09548],[-0.9467,53.08198],[-0.95316,53.08296],[-0.95737,53.07894]]]}},{"type":"Feature","properties":{"c":"E01028347","n":"Newark and Sherwood 008C","d":10,"s":4.7,"r":31220,"id":9,"ed":10,"hd":9,"cd":9,"bd":7,"ld":6,"p":1493,"wbi":93.3,"wir":0.6,"wot":2.5,"ind":0.3,"pak":0.1,"chi":0.3,"oas":0.1,"bca":0.2,"mwc":0.1,"mwa":0.2,"mwas":0.8,"mot":0.5,"ara":0.4,"oet":0.4,"a04":2.9,"a511":7.8,"a1217":8.3,"a1824":6.9,"a2534":6.6,"a3544":9.3,"a4559":22.5,"a6074":21.8,"a75p":13.8},"geometry":{"type":"Polygon","coordinates":[[[-0.95737,53.07894],[-0.95284,53.07707],[-0.95177,53.07002],[-0.95959,53.07134],[-0.95844,53.07536],[-0.96846,53.07448],[-0.96242,53.08247],[-0.95737,53.07894]]]}},{"type":"Feature","properties":{"c":"E01028348","n":"Newark and Sherwood 008D","d":9,"s":7.8,"r":27687,"id":7,"ed":9,"hd":7,"cd":9,"bd":5,"ld":7,"p":1741,"wbi":92.4,"wir":0.4,"wot":2.9,"ind":0.5,"pak":0.3,"chi":0.3,"oas":0.2,"bca":0.3,"baf":0.1,"bot":0.1,"mwc":1.1,"mwa":0.2,"mwas":0.5,"mot":0.2,"ara":0.3,"oet":0.1,"a04":3.2,"a511":5.4,"a1217":13.6,"a1824":22.5,"a2534":6.4,"a3544":7.5,"a4559":15.2,"a6074":16.1,"a75p":10.1},"geometry":{"type":"Polygon","coordinates":[[[-0.96242,53.08247],[-0.96846,53.07448],[-0.95844,53.07536],[-0.95959,53.07134],[-0.95177,53.07002],[-0.94933,53.05876],[-0.94272,53.05696],[-0.94513,53.05588],[-0.98485,53.04623],[-1.00236,53.05643],[-1.02089,53.05899],[-1.02125,53.05902],[-1.02748,53.06522],[-1.02484,53.06818],[-1.01426,53.07072],[-1.01504,53.06511],[-0.99841,53.07534],[-0.98474,53.07859],[-0.97074,53.09095],[-0.9629,53.08711],[-0.96242,53.08247]]]}},{"type":"Feature","properties":{"c":"E01028349","n":"Newark and Sherwood 003D","d":6,"s":16.5,"r":17726,"id":9,"ed":8,"hd":8,"cd":8,"bd":1,"ld":1,"p":1579,"wbi":95.9,"wir":0.8,"wot":2.2,"ind":0.3,"chi":0.1,"oas":0.1,"bca":0.1,"mwc":0.3,"mwa":0.1,"mwas":0.1,"mot":0.1,"oet":0.1,"a04":3.9,"a511":5.3,"a1217":5.4,"a1824":5.2,"a2534":9.0,"a3544":9.6,"a4559":23.3,"a6074":25.9,"a75p":12.4},"geometry":{"type":"Polygon","coordinates":[[[-0.78036,53.1964],[-0.7813,53.19274],[-0.79706,53.19591],[-0.82669,53.19355],[-0.81683,53.18404],[-0.81543,53.17599],[-0.81209,53.17911],[-0.78666,53.17872],[-0.78541,53.16857],[-0.79281,53.17089],[-0.80074,53.16819],[-0.80011,53.15808],[-0.78677,53.15924],[-0.79746,53.15207],[-0.79188,53.14582],[-0.79143,53.14206],[-0.79939,53.14224],[-0.80482,53.13654],[-0.81631,53.13412],[-0.82259,53.13844],[-0.84324,53.14311],[-0.86456,53.13384],[-0.87485,53.13588],[-0.87465,53.14456],[-0.91155,53.15249],[-0.91237,53.15764],[-0.91183,53.16099],[-0.90184,53.16428],[-0.87011,53.15778],[-0.85349,53.16048],[-0.8456,53.17253],[-0.83997,53.17428],[-0.8486,53.1768],[-0.84889,53.18468],[-0.85298,53.18623],[-0.85163,53.19025],[-0.84276,53.19119],[-0.85441,53.19127],[-0.85262,53.19589],[-0.85782,53.197],[-0.87981,53.19829],[-0.86943,53.21671],[-0.85784,53.21221],[-0.8485,53.21531],[-0.84821,53.21866],[-0.8308,53.21757],[-0.83696,53.21366],[-0.83052,53.21283],[-0.83206,53.20673],[-0.82241,53.20168],[-0.81572,53.20492],[-0.78729,53.20457],[-0.79008,53.19915],[-0.78036,53.1964]]]}},{"type":"Feature","properties":{"c":"E01028350","n":"Newark and Sherwood 003E","d":6,"s":15.9,"r":18383,"id":6,"ed":8,"hd":6,"cd":9,"bd":2,"ld":2,"p":1249,"wbi":96.3,"wir":0.2,"wot":1.6,"ind":0.2,"chi":0.3,"oas":0.1,"mwc":0.2,"mwa":0.2,"mwas":0.3,"mot":0.4,"ara":0.1,"oet":0.2,"a04":4.4,"a511":7.7,"a1217":7.1,"a1824":5.8,"a2534":10.5,"a3544":10.0,"a4559":24.2,"a6074":21.0,"a75p":9.4},"geometry":{"type":"Polygon","coordinates":[[[-0.7813,53.19274],[-0.77793,53.18652],[-0.79538,53.18107],[-0.78666,53.17872],[-0.81209,53.17911],[-0.81543,53.17599],[-0.81683,53.18404],[-0.82669,53.19355],[-0.79706,53.19591],[-0.7813,53.19274]]]}},{"type":"Feature","properties":{"c":"E01028351","n":"Newark and Sherwood 013D","d":9,"s":7.7,"r":27788,"id":10,"ed":10,"hd":8,"cd":10,"bd":2,"ld":7,"p":1282,"wbi":92.7,"wir":0.9,"wgy":0.1,"wot":1.0,"ind":1.6,"ban":0.1,"chi":0.3,"oas":0.7,"baf":0.1,"mwc":0.5,"mwa":0.2,"mwas":1.4,"mot":0.4,"oet":0.1,"a04":3.0,"a511":8.2,"a1217":7.4,"a1824":5.8,"a2534":5.2,"a3544":7.8,"a4559":27.0,"a6074":21.8,"a75p":13.8},"geometry":{"type":"Polygon","coordinates":[[[-0.94513,53.05588],[-0.91346,53.03619],[-0.90209,53.03848],[-0.91012,53.03593],[-0.92702,53.02381],[-0.9354,53.02478],[-0.95056,53.01883],[-0.97015,53.02353],[-0.98127,53.03105],[-0.99899,53.03531],[-0.99783,53.03972],[-1.00792,53.04266],[-1.01227,53.04902],[-1.0257,53.05512],[-1.02089,53.05899],[-1.00236,53.05643],[-0.98485,53.04623],[-0.94513,53.05588]]]}},{"type":"Feature","properties":{"c":"E01028352","n":"Newark and Sherwood 012E","d":9,"s":6.1,"r":29637,"id":10,"ed":10,"hd":10,"cd":10,"bd":2,"ld":6,"p":1158,"wbi":95.5,"wir":0.8,"wgy":0.1,"wot":1.1,"ind":0.2,"oas":0.3,"bca":0.1,"baf":0.2,"mwc":0.3,"mwas":0.6,"mot":0.7,"oet":0.2,"a04":3.3,"a511":6.8,"a1217":7.0,"a1824":6.5,"a2534":5.2,"a3544":8.7,"a4559":23.6,"a6074":26.0,"a75p":12.9},"geometry":{"type":"Polygon","coordinates":[[[-0.85969,53.06793],[-0.85415,53.06262],[-0.86325,53.05965],[-0.86198,53.05163],[-0.87247,53.04935],[-0.87631,53.04356],[-0.88723,53.05429],[-0.89463,53.05483],[-0.90505,53.04869],[-0.90209,53.03848],[-0.91346,53.03619],[-0.94513,53.05588],[-0.94272,53.05696],[-0.92716,53.06369],[-0.91262,53.06371],[-0.91443,53.06614],[-0.90642,53.07204],[-0.89899,53.07155],[-0.89057,53.07718],[-0.86578,53.06704],[-0.85969,53.06793]]]}},{"type":"Feature","properties":{"c":"E01028353","n":"Newark and Sherwood 004D","d":8,"s":11.1,"r":23649,"id":8,"ed":7,"hd":8,"cd":9,"bd":3,"ld":6,"p":2770,"wbi":94.4,"wir":0.5,"wgy":0.2,"wro":0.1,"wot":2.2,"ind":0.1,"pak":0.1,"ban":0.2,"chi":0.1,"oas":0.1,"bca":0.1,"baf":0.4,"mwc":0.5,"mwa":0.1,"mwas":0.3,"mot":0.4,"a04":4.3,"a511":6.9,"a1217":6.4,"a1824":5.9,"a2534":8.4,"a3544":10.0,"a4559":22.9,"a6074":23.3,"a75p":11.8},"geometry":{"type":"Polygon","coordinates":[[[-0.77413,53.13532],[-0.77419,53.13073],[-0.76838,53.12733],[-0.75954,53.12113],[-0.75772,53.11215],[-0.74857,53.10351],[-0.73194,53.10055],[-0.72959,53.09782],[-0.70615,53.08338],[-0.71036,53.07938],[-0.69848,53.07547],[-0.69881,53.06775],[-0.6953,53.06704],[-0.70154,53.06366],[-0.71347,53.06605],[-0.7162,53.05906],[-0.7226,53.05992],[-0.73098,53.0544],[-0.74543,53.05412],[-0.74835,53.0552],[-0.75457,53.05604],[-0.75244,53.06294],[-0.76166,53.066],[-0.76646,53.07226],[-0.76993,53.07134],[-0.77465,53.08367],[-0.78671,53.09373],[-0.7989,53.10142],[-0.79302,53.10795],[-0.80422,53.11048],[-0.80182,53.11695],[-0.80834,53.12276],[-0.80191,53.13374],[-0.79605,53.13308],[-0.79188,53.13591],[-0.79143,53.14206],[-0.79188,53.14582],[-0.77413,53.13532]]]}},{"type":"Feature","properties":{"c":"E01033394","n":"Newark and Sherwood 012G","d":8,"s":9.7,"r":25305,"id":8,"ed":8,"hd":6,"cd":8,"bd":4,"ld":8,"p":1518,"wbi":94.6,"wir":0.3,"wgy":0.2,"wot":2.5,"ind":0.1,"oas":0.5,"bca":0.3,"baf":0.1,"bot":0.1,"mwc":0.6,"mwa":0.1,"mwas":0.3,"mot":0.2,"oet":0.1,"a04":3.2,"a511":6.6,"a1217":5.0,"a1824":5.3,"a2534":12.3,"a3544":8.9,"a4559":22.1,"a6074":20.6,"a75p":16.0},"geometry":{"type":"Polygon","coordinates":[[[-0.84045,53.06681],[-0.83031,53.06213],[-0.83154,53.05849],[-0.8262,53.05861],[-0.81228,53.05749],[-0.80597,53.05726],[-0.80351,53.04868],[-0.80266,53.02491],[-0.82537,53.02465],[-0.82511,53.02059],[-0.87631,53.04356],[-0.87247,53.04935],[-0.86198,53.05163],[-0.85347,53.04649],[-0.84511,53.05401],[-0.85075,53.05714],[-0.84412,53.06338],[-0.85415,53.06262],[-0.85969,53.06793],[-0.84734,53.07487],[-0.84045,53.06681]]]}},{"type":"Feature","properties":{"c":"E01033770","n":"Newark and Sherwood 001G","d":5,"s":18.6,"r":15824,"id":6,"ed":4,"hd":2,"cd":5,"bd":5,"ld":9,"p":1373,"wbi":89.7,"wir":0.2,"wgy":2.5,"wot":2.8,"ind":0.5,"pak":0.1,"ban":0.1,"chi":0.2,"oas":0.5,"bca":0.2,"bot":0.1,"mwc":0.4,"mwa":0.2,"mwas":0.4,"mot":0.3,"ara":0.5,"oet":1.4,"a04":5.6,"a511":6.1,"a1217":5.0,"a1824":7.0,"a2534":19.5,"a3544":14.0,"a4559":22.6,"a6074":14.6,"a75p":5.7},"geometry":{"type":"Polygon","coordinates":[[[-1.00198,53.20084],[-1.00212,53.19245],[-1.00403,53.19145],[-1.01479,53.19481],[-1.01146,53.19853],[-1.01471,53.20253],[-1.00711,53.20482],[-1.00198,53.20084]]]}},{"type":"Feature","properties":{"c":"E01033771","n":"Newark and Sherwood 001H","d":5,"s":21.4,"r":13600,"id":5,"ed":4,"hd":2,"cd":6,"bd":6,"ld":5,"p":1322,"wbi":96.4,"wir":0.3,"wgy":0.9,"wro":0.5,"wot":0.5,"ind":0.4,"oas":0.1,"bca":0.3,"baf":0.3,"mwc":0.1,"mwa":0.1,"oet":0.2,"a04":2.2,"a511":5.0,"a1217":4.1,"a1824":3.4,"a2534":7.5,"a3544":8.3,"a4559":19.8,"a6074":29.0,"a75p":20.7},"geometry":{"type":"Polygon","coordinates":[[[-1.01146,53.19853],[-1.01479,53.19481],[-1.00403,53.19145],[-1.00596,53.18894],[-1.03301,53.18344],[-1.03315,53.19325],[-1.02734,53.19806],[-1.03672,53.19889],[-1.03484,53.20378],[-1.0276,53.20125],[-1.02583,53.20601],[-1.02429,53.20157],[-1.01146,53.19853]]]}},{"type":"Feature","properties":{"c":"E01033772","n":"Newark and Sherwood 002F","d":7,"s":11.4,"r":23350,"id":6,"ed":6,"hd":6,"cd":6,"bd":5,"ld":10,"p":1510,"wbi":87.5,"wir":0.1,"wgy":0.4,"wot":3.6,"ind":0.1,"chi":0.2,"oas":0.2,"bca":0.2,"baf":3.6,"bot":1.2,"mwc":0.9,"mwa":0.4,"mwas":0.6,"mot":0.6,"oet":0.5,"a04":11.6,"a511":9.9,"a1217":5.4,"a1824":7.2,"a2534":28.4,"a3544":15.6,"a4559":12.8,"a6074":6.8,"a75p":2.2},"geometry":{"type":"Polygon","coordinates":[[[-1.12067,53.17411],[-1.12394,53.17261],[-1.11926,53.1701],[-1.12488,53.16618],[-1.12875,53.15967],[-1.13616,53.16462],[-1.14626,53.16929],[-1.152,53.17275],[-1.15298,53.17532],[-1.13612,53.18868],[-1.12779,53.18989],[-1.11957,53.19065],[-1.12334,53.18814],[-1.12067,53.17411]]]}},{"type":"Feature","properties":{"c":"E01033773","n":"Newark and Sherwood 002G","d":9,"s":6.1,"r":29664,"id":10,"ed":8,"hd":5,"cd":8,"bd":5,"ld":10,"p":1707,"wbi":92.0,"wir":0.2,"wot":3.1,"ind":0.1,"pak":0.1,"chi":0.9,"oas":0.1,"bca":0.1,"baf":0.8,"bot":0.4,"mwc":0.8,"mwa":0.4,"mwas":0.5,"mot":0.3,"ara":0.1,"oet":0.1,"a04":7.6,"a511":11.0,"a1217":9.1,"a1824":8.1,"a2534":17.5,"a3544":17.0,"a4559":21.5,"a6074":6.8,"a75p":1.3},"geometry":{"type":"Polygon","coordinates":[[[-1.11696,53.16488],[-1.12488,53.16618],[-1.11926,53.1701],[-1.12394,53.17261],[-1.12067,53.17411],[-1.11379,53.17834],[-1.10833,53.17743],[-1.1132,53.17325],[-1.10757,53.17065],[-1.11696,53.16488]]]}},{"type":"Feature","properties":{"c":"E01033774","n":"Newark and Sherwood 002H","d":4,"s":24.8,"r":11244,"id":4,"ed":3,"hd":2,"cd":5,"bd":7,"ld":8,"p":1430,"wbi":95.6,"wir":0.3,"wgy":0.1,"wot":1.5,"ind":0.6,"ban":0.1,"chi":0.4,"bca":0.3,"baf":0.5,"bot":0.1,"mwc":0.1,"mwas":0.1,"mot":0.1,"oet":0.3,"a04":7.9,"a511":10.4,"a1217":7.1,"a1824":8.6,"a2534":14.7,"a3544":13.4,"a4559":20.9,"a6074":12.1,"a75p":4.7},"geometry":{"type":"Polygon","coordinates":[[[-1.11696,53.16488],[-1.11571,53.16265],[-1.12802,53.15905],[-1.12875,53.15967],[-1.12488,53.16618],[-1.11696,53.16488]]]}},{"type":"Feature","properties":{"c":"E01033777","n":"Newark and Sherwood 012H","d":7,"s":12.3,"r":22243,"id":5,"ed":8,"hd":5,"cd":7,"bd":5,"ld":9,"p":1506,"wbi":85.7,"wir":0.1,"wgy":0.7,"wro":0.5,"wot":7.9,"ind":0.7,"pak":0.6,"chi":0.1,"oas":0.3,"baf":0.7,"bot":0.1,"mwc":1.1,"mwa":0.2,"mwas":0.2,"mot":0.9,"ara":0.1,"a04":7.7,"a511":12.9,"a1217":8.2,"a1824":7.5,"a2534":15.3,"a3544":19.5,"a4559":20.2,"a6074":7.1,"a75p":1.6},"geometry":{"type":"Polygon","coordinates":[[[-0.76133,53.05302],[-0.76676,53.04593],[-0.77745,53.04673],[-0.77904,53.05],[-0.77855,53.05029],[-0.76753,53.05661],[-0.76133,53.05302]]]}},{"type":"Feature","properties":{"c":"E01033780","n":"Newark and Sherwood 012I","d":10,"s":4.5,"r":31415,"id":10,"ed":9,"hd":9,"cd":8,"bd":5,"ld":10,"p":1809,"wbi":87.6,"wir":0.2,"wgy":0.2,"wot":4.4,"ind":1.4,"pak":0.2,"chi":0.6,"oas":0.2,"bca":0.4,"baf":1.7,"bot":0.6,"mwc":0.8,"mwa":0.1,"mwas":0.5,"mot":0.6,"oet":0.4,"a04":5.0,"a511":11.7,"a1217":9.4,"a1824":6.8,"a2534":10.0,"a3544":17.3,"a4559":23.7,"a6074":10.5,"a75p":5.5},"geometry":{"type":"Polygon","coordinates":[[[-0.75344,53.04806],[-0.76083,53.02941],[-0.77667,53.02471],[-0.78841,53.02585],[-0.79021,53.02213],[-0.79909,53.02131],[-0.80291,53.01741],[-0.80266,53.02491],[-0.80351,53.04868],[-0.7972,53.0428],[-0.79087,53.04461],[-0.77904,53.05],[-0.77745,53.04673],[-0.76676,53.04593],[-0.76133,53.05302],[-0.75344,53.04806]]]}}]}